rl_visualizer/__init__.py
rl_visualizer/visualizer.py
rl_visualizer-0.1.1.dist-info/LICENSE
rl_visualizer-0.1.1.dist-info/METADATA
rl_visualizer-0.1.1.dist-info/WHEEL
rl_visualizer-0.1.1.dist-info/top_level.txt
rl_visualizer-0.1.1.dist-info/RECORD
